AUTHORS.rst
CONTRIBUTING.rst
LICENSE.txt
MANIFEST.in
README.rst
setup.cfg
setup.py
versioneer.py
dask_imread/__init__.py
dask_imread/_version.py
dask_imread.egg-info/PKG-INFO
dask_imread.egg-info/SOURCES.txt
dask_imread.egg-info/dependency_links.txt
dask_imread.egg-info/not-zip-safe
dask_imread.egg-info/requires.txt
dask_imread.egg-info/top_level.txt
docs/Makefile
docs/api.rst
docs/authors.rst
docs/conf.py
docs/contributing.rst
docs/index.rst
docs/installation.rst
docs/make.bat
docs/readme.rst
docs/usage.rst
tests/__init__.py
tests/test_dask_imread.py